ddddocr/__init__.py
ddddocr/common.onnx
ddddocr/common_det.onnx
ddddocr/common_old.onnx
ddddocr_py311-1.4.7.1.dist-info/LICENSE
ddddocr_py311-1.4.7.1.dist-info/METADATA
ddddocr_py311-1.4.7.1.dist-info/WHEEL
ddddocr_py311-1.4.7.1.dist-info/top_level.txt
ddddocr_py311-1.4.7.1.dist-info/RECORD
