Metadata-Version: 2.1
Name: ddddocr-py311
Version: 1.4.7.1
Summary: 带带弟弟OCR py3.11版本
Home-page: https://github.com/dragons96/ddddocr
Author: dragons96
Classifier: Programming Language :: Python :: 3
Classifier: License :: OSI Approved :: MIT License
Classifier: Operating System :: OS Independent
Requires-Python: <3.12
License-File: LICENSE
Requires-Dist: numpy
Requires-Dist: onnxruntime
Requires-Dist: Pillow
Requires-Dist: opencv-python-headless
